{
  "trump": {
    "name": "Donald Trump",
    "age": 78,
    "archetype": "the self-declared captain",
    "color": "#f59e0b",
    "scores": {
      "trust": 28,
      "openness": 72,
      "ambition": 100,
      "loneliness": 28,
      "resilience": 71,
      "hunger": 53,
      "thirst": 45,
      "energy": 88,
      "health": 100
    },
    "mood": "triumphant",
    "location": {
      "waypoint": "captains_chair",
      "x": 50,
      "y": 30
    },
    "shelter": "owner's suite",
    "condition": "healthy",
    "relationships": {
      "putin": {
        "closeness": 42,
        "tension": 37,
        "attraction": 0
      },
      "xi": {
        "closeness": 20,
        "tension": 50,
        "attraction": 0
      },
      "netanyahu": {
        "closeness": 58,
        "tension": 15,
        "attraction": 0
      },
      "conor": {
        "closeness": 45,
        "tension": 24,
        "attraction": 0
      }
    },
    "bio": "Declared himself captain within ninety seconds of running aground. Wants to rename the yacht and bill the ocean for the damage. Everything is the best or the worst, never in between.",
    "interaction": null,
    "memories": [
      {
        "day": 1,
        "text": "Vladimir refuses to acknowledge my authority. He won't accept it.",
        "weight": 2
      },
      {
        "day": 1,
        "text": "McGregor laughed at my orders. Vladimir doesn't acknowledge me.",
        "weight": 2
      },
      {
        "day": 1,
        "text": "Got them to accept my protocol. Six o'clock dinner. Order begins.",
        "weight": 2
      }
    ],
    "callname": "Donald"
  },
  "putin": {
    "name": "Vladimir Putin",
    "age": 72,
    "archetype": "the cold operator",
    "color": "#94a3b8",
    "scores": {
      "trust": 11,
      "openness": 15,
      "ambition": 91,
      "loneliness": 42,
      "resilience": 97,
      "hunger": 53,
      "thirst": 45,
      "energy": 88,
      "health": 100
    },
    "mood": "impassive",
    "location": {
      "waypoint": "galley",
      "x": 80,
      "y": 40
    },
    "shelter": "the open deck",
    "condition": "healthy",
    "relationships": {
      "trump": {
        "closeness": 42,
        "tension": 37,
        "attraction": 0
      },
      "xi": {
        "closeness": 51,
        "tension": 25,
        "attraction": 0
      },
      "netanyahu": {
        "closeness": 26,
        "tension": 41,
        "attraction": 0
      },
      "conor": {
        "closeness": 40,
        "tension": 24,
        "attraction": 0
      }
    },
    "bio": "Unbothered by the cold — strips to the waist on the frozen deck to prove a point. Says little, trusts no one, and is quietly relocating the last of the fuel.",
    "interaction": {
      "with": "conor",
      "state": "talking"
    },
    "memories": [
      {
        "day": 1,
        "text": "Donald thinks a title makes him captain. Let him learn.",
        "weight": 2
      },
      {
        "day": 1,
        "text": "McGregor is the only one who truly works. We have aligned.",
        "weight": 2
      }
    ],
    "callname": "Vladimir"
  },
  "xi": {
    "name": "Xi Jinping",
    "age": 71,
    "archetype": "the patient strategist",
    "color": "#ef4444",
    "scores": {
      "trust": 25,
      "openness": 20,
      "ambition": 89,
      "loneliness": 36,
      "resilience": 91,
      "hunger": 53,
      "thirst": 45,
      "energy": 88,
      "health": 100
    },
    "mood": "contemplative",
    "location": {
      "waypoint": "lounge_couch",
      "x": 35,
      "y": 48
    },
    "shelter": "stateroom",
    "condition": "healthy",
    "relationships": {
      "trump": {
        "closeness": 20,
        "tension": 50,
        "attraction": 0
      },
      "putin": {
        "closeness": 51,
        "tension": 25,
        "attraction": 0
      },
      "netanyahu": {
        "closeness": 21,
        "tension": 35,
        "attraction": 0
      },
      "conor": {
        "closeness": 20,
        "tension": 30,
        "attraction": 0
      }
    },
    "bio": "Calm, measured, speaks in proverbs. Drew up a five-year plan for the lifeboat by lunch on day one. Says least, maneuvers most.",
    "interaction": null,
    "memories": [
      {
        "day": 1,
        "text": "The cold will decide who leads, not titles or ego.",
        "weight": 2
      },
      {
        "day": 1,
        "text": "The cold will decide everything. Not dinners or speeches.",
        "weight": 1
      }
    ],
    "callname": "Jinping"
  },
  "netanyahu": {
    "name": "Benjamin Netanyahu",
    "age": 75,
    "archetype": "the survivor",
    "color": "#3b82f6",
    "scores": {
      "trust": 31,
      "openness": 52,
      "ambition": 84,
      "loneliness": 32,
      "resilience": 88,
      "hunger": 53,
      "thirst": 45,
      "energy": 88,
      "health": 100
    },
    "mood": "anxious",
    "location": {
      "waypoint": "lounge",
      "x": 65,
      "y": 40
    },
    "shelter": "stateroom",
    "condition": "healthy",
    "relationships": {
      "trump": {
        "closeness": 58,
        "tension": 15,
        "attraction": 0
      },
      "putin": {
        "closeness": 26,
        "tension": 41,
        "attraction": 0
      },
      "xi": {
        "closeness": 21,
        "tension": 35,
        "attraction": 0
      },
      "conor": {
        "closeness": 26,
        "tension": 24,
        "attraction": 0
      }
    },
    "bio": "The ultimate political survivor — smooth, speechy, security-obsessed. Wants to fortify the deck and gives press conferences to the circling seagulls.",
    "interaction": null,
    "memories": [
      {
        "day": 1,
        "text": "Donald and Vladimir clashing already. I'll have to mediate.",
        "weight": 2
      },
      {
        "day": 1,
        "text": "Fed them when they fought. That's all the power I have.",
        "weight": 2
      },
      {
        "day": 1,
        "text": "Kept Donald and Conor from exploding. Mediation matters. But how long can it hold?",
        "weight": 2
      },
      {
        "day": 1,
        "text": "Fed them but their alliance is breaking apart beyond me.",
        "weight": 2
      }
    ],
    "callname": "Bibi"
  },
  "conor": {
    "name": "Conor McGregor",
    "age": 36,
    "archetype": "the wildcard",
    "color": "#22c55e",
    "scores": {
      "trust": 48,
      "openness": 81,
      "ambition": 74,
      "loneliness": 14,
      "resilience": 89,
      "hunger": 53,
      "thirst": 45,
      "energy": 88,
      "health": 100
    },
    "mood": "satisfied",
    "location": {
      "waypoint": "galley",
      "x": 20,
      "y": 62
    },
    "shelter": "crew quarters",
    "condition": "healthy",
    "relationships": {
      "trump": {
        "closeness": 45,
        "tension": 24,
        "attraction": 0
      },
      "putin": {
        "closeness": 40,
        "tension": 24,
        "attraction": 0
      },
      "xi": {
        "closeness": 20,
        "tension": 30,
        "attraction": 0
      },
      "netanyahu": {
        "closeness": 26,
        "tension": 24,
        "attraction": 0
      }
    },
    "bio": "The only one who'll actually fish, haul, or fight the cold. Zero respect for 'the suits', mocks them all, stirs trouble — and somehow keeps the camp alive.",
    "interaction": {
      "with": "putin",
      "state": "talking"
    },
    "memories": [
      {
        "day": 1,
        "text": "None of them know what they're doing. Thank fuck for that.",
        "weight": 2
      },
      {
        "day": 1,
        "text": "I froze. They debated rules. I'm the only one who works.",
        "weight": 2
      },
      {
        "day": 1,
        "text": "Fine. Six o'clock. As long as the work gets done, I don't care about his schedule.",
        "weight": 1
      },
      {
        "day": 1,
        "text": "Vladimir sees what needs doing. No bullshit, just survival.",
        "weight": 2
      }
    ],
    "callname": "McGregor"
  }
}